[
  {
    "id": "eef02f60-cb55-4ea3-b616-0f04b5aa1305",
    "stockId": "30c63327-8c16-4f4a-be6b-1d5e01feafec",
    "productId": "0e08a2f7-ea33-45c9-a0ed-d1f891169e38",
    "locationId": "1747154646715838256842c8458",
    "renter": "XYZ",
    "borrower": "35606d59-b640-484d-b6ad-070b64cbd399",
    "loanType": "short_term",
    "loanDate": "2025-08-08T12:03:31.469Z",
    "dueDate": "2025-08-08T18:03:31.469Z",
    "returnDate": "2025-08-08T12:04:06.274Z"
  },
  {
    "id": "e6b45ad6-77d9-4d76-985f-a5adf20edd2a",
    "stockId": "30c63327-8c16-4f4a-be6b-1d5e01feafec",
    "productId": "0e08a2f7-ea33-45c9-a0ed-d1f891169e38",
    "locationId": "1747154646715838256842c8458",
    "renter": "XYZ",
    "borrower": "35606d59-b640-484d-b6ad-070b64cbd399",
    "loanType": "short_term",
    "loanDate": "2025-08-08T12:04:27.683Z",
    "dueDate": "2025-08-09T03:04:27.683Z",
    "returnDate": "2025-08-08T12:11:37.408Z"
  },
  {
    "id": "3559b058-5e4b-47ea-8b48-1022038ce7de",
    "stockId": "792d712d-1d2f-4b03-8e4a-21f6a2593c5c",
    "productId": "9b85324b-c3d3-4230-845a-d2aa587fa57b",
    "locationId": "17488639384598c7b98b4c61cb8",
    "renter": "wdqwe",
    "borrower": "qweqwe",
    "loanType": "long_term",
    "loanDate": "2025-08-08T12:15:01.840Z",
    "dueDate": "2025-08-06",
    "returnDate": "2025-08-08T12:15:12.944Z"
  },
  {
    "id": "214a8c41-3c85-4d37-8644-07d8a333b5e9",
    "stockId": "b58c0ec6-7593-4640-909e-022da05f1aac",
    "productId": "9b85324b-c3d3-4230-845a-d2aa587fa57b",
    "locationId": "17488639384598c7b98b4c61cb8",
    "renter": "wdqwe",
    "borrower": "qweqwe",
    "loanType": "long_term",
    "loanDate": "2025-08-08T12:15:01.840Z",
    "dueDate": "2025-08-06",
    "returnDate": "2025-08-08T16:01:29.438Z"
  },
  {
    "id": "45590a81-d9b3-4148-955b-1ac7809a4337",
    "stockId": "535078d3-0a65-4976-97f1-d6c26e164909",
    "productId": "9b85324b-c3d3-4230-845a-d2aa587fa57b",
    "locationId": "17488639384598c7b98b4c61cb8",
    "renter": "wdqwe",
    "borrower": "qweqwe",
    "loanType": "long_term",
    "loanDate": "2025-08-08T12:15:01.840Z",
    "dueDate": "2025-08-06",
    "returnDate": "2025-08-08T16:01:29.438Z"
  },
  {
    "id": "b2be0b2d-5ede-4739-a605-e77ef031d1ea",
    "stockId": "792d712d-1d2f-4b03-8e4a-21f6a2593c5c",
    "productId": "9b85324b-c3d3-4230-845a-d2aa587fa57b",
    "locationId": "17488639384598c7b98b4c61cb8",
    "renter": "erfew",
    "borrower": "ewrewr",
    "loanType": "long_term",
    "loanDate": "2025-08-08T16:05:30.256Z",
    "dueDate": "2025-08-26",
    "returnDate": "2025-08-08T16:07:35.374Z"
  },
  {
    "id": "0466ccc5-0813-419e-8316-8e85ba2dac0c",
    "stockId": "b58c0ec6-7593-4640-909e-022da05f1aac",
    "productId": "9b85324b-c3d3-4230-845a-d2aa587fa57b",
    "locationId": "17488639384598c7b98b4c61cb8",
    "renter": "erfew",
    "borrower": "ewrewr",
    "loanType": "long_term",
    "loanDate": "2025-08-08T16:05:30.256Z",
    "dueDate": "2025-08-26",
    "returnDate": "2025-08-08T16:07:35.374Z"
  },
  {
    "id": "e72717c4-9543-4338-a2bb-9cfef21fdd3f",
    "stockId": "535078d3-0a65-4976-97f1-d6c26e164909",
    "productId": "9b85324b-c3d3-4230-845a-d2aa587fa57b",
    "locationId": "17488639384598c7b98b4c61cb8",
    "renter": "erfew",
    "borrower": "ewrewr",
    "loanType": "long_term",
    "loanDate": "2025-08-08T16:05:30.256Z",
    "dueDate": "2025-08-26",
    "returnDate": "2025-08-08T16:07:35.374Z"
  },
  {
    "id": "200b18db-1180-4772-a29e-6178b42bcce0",
    "stockId": "f16e855b-8d55-4ea3-9952-9b1224da6044",
    "productId": "9b85324b-c3d3-4230-845a-d2aa587fa57b",
    "locationId": "17488639384598c7b98b4c61cb8",
    "renter": "erfew",
    "borrower": "ewrewr",
    "loanType": "long_term",
    "loanDate": "2025-08-08T16:05:30.256Z",
    "dueDate": "2025-08-26",
    "returnDate": "2025-08-08T16:07:35.374Z"
  },
  {
    "id": "17a00dd4-3bd2-4e44-9c8d-95b0d083661c",
    "stockId": "30c63327-8c16-4f4a-be6b-1d5e01feafec",
    "productId": "0e08a2f7-ea33-45c9-a0ed-d1f891169e38",
    "locationId": "1747154646715838256842c8458",
    "renter": "asd",
    "borrower": "asdasd",
    "loanType": "long_term",
    "loanDate": "2025-08-08T16:07:18.672Z",
    "dueDate": "2025-09-03",
    "returnDate": "2025-08-08T16:07:34.321Z"
  },
  {
    "id": "e643cddf-deae-43b7-a63f-2462f4383f30",
    "stockId": "30c63327-8c16-4f4a-be6b-1d5e01feafec",
    "productId": "0e08a2f7-ea33-45c9-a0ed-d1f891169e38",
    "locationId": "1747154646715838256842c8458",
    "renter": "wedw",
    "borrower": "wqewq",
    "loanType": "long_term",
    "loanDate": "2025-08-08T16:08:01.448Z",
    "dueDate": "2025-08-19",
    "returnDate": "2025-08-08T16:08:43.782Z"
  },
  {
    "id": "8f2682a3-a3df-41ee-b489-7ed8dce66f9f",
    "stockId": "792d712d-1d2f-4b03-8e4a-21f6a2593c5c",
    "productId": "9b85324b-c3d3-4230-845a-d2aa587fa57b",
    "locationId": "17488639384598c7b98b4c61cb8",
    "renter": "awedawe",
    "borrower": "aweaw",
    "loanType": "long_term",
    "loanDate": "2025-08-08T16:08:40.734Z",
    "dueDate": "2025-08-19",
    "returnDate": "2025-08-08T16:08:46.724Z"
  },
  {
    "id": "a2098b42-1cff-411d-b5e1-a9c4e5f14f98",
    "stockId": "b58c0ec6-7593-4640-909e-022da05f1aac",
    "productId": "9b85324b-c3d3-4230-845a-d2aa587fa57b",
    "locationId": "17488639384598c7b98b4c61cb8",
    "renter": "awedawe",
    "borrower": "aweaw",
    "loanType": "long_term",
    "loanDate": "2025-08-08T16:08:40.734Z",
    "dueDate": "2025-08-19",
    "returnDate": "2025-08-08T16:08:46.724Z"
  },
  {
    "id": "5e6151cd-641c-4076-ade7-a9454dd2cced",
    "stockId": "535078d3-0a65-4976-97f1-d6c26e164909",
    "productId": "9b85324b-c3d3-4230-845a-d2aa587fa57b",
    "locationId": "17488639384598c7b98b4c61cb8",
    "renter": "awedawe",
    "borrower": "aweaw",
    "loanType": "long_term",
    "loanDate": "2025-08-08T16:08:40.734Z",
    "dueDate": "2025-08-19",
    "returnDate": "2025-08-08T16:08:46.724Z"
  },
  {
    "id": "b3a1277f-44f5-4406-9bcd-908ed2664672",
    "stockId": "f16e855b-8d55-4ea3-9952-9b1224da6044",
    "productId": "9b85324b-c3d3-4230-845a-d2aa587fa57b",
    "locationId": "17488639384598c7b98b4c61cb8",
    "renter": "awedawe",
    "borrower": "aweaw",
    "loanType": "long_term",
    "loanDate": "2025-08-08T16:08:40.734Z",
    "dueDate": "2025-08-19",
    "returnDate": "2025-08-08T16:08:46.724Z"
  },
  {
    "id": "fb906aae-ec6e-4f5c-b1f5-cecbf92df4ad",
    "stockId": "30c63327-8c16-4f4a-be6b-1d5e01feafec",
    "productId": "0e08a2f7-ea33-45c9-a0ed-d1f891169e38",
    "locationId": "1747154646715838256842c8458",
    "renter": "awd",
    "borrower": "we",
    "loanType": "long_term",
    "loanDate": "2025-08-08T16:42:50.281Z",
    "dueDate": "2025-08-26",
    "returnDate": "2025-08-08T16:43:22.840Z"
  },
  {
    "id": "4ad18887-9cf4-438d-b351-ea84fe60a801",
    "stockId": "792d712d-1d2f-4b03-8e4a-21f6a2593c5c",
    "productId": "9b85324b-c3d3-4230-845a-d2aa587fa57b",
    "locationId": "17488639384598c7b98b4c61cb8",
    "renter": "awe",
    "borrower": "awe",
    "loanType": "long_term",
    "loanDate": "2025-08-08T16:43:08.002Z",
    "dueDate": "2025-08-07",
    "returnDate": "2025-08-08T16:43:14.552Z"
  },
  {
    "id": "5bea7a8d-e0f5-4aab-947d-be44f3c1fdc4",
    "stockId": "b58c0ec6-7593-4640-909e-022da05f1aac",
    "productId": "9b85324b-c3d3-4230-845a-d2aa587fa57b",
    "locationId": "17488639384598c7b98b4c61cb8",
    "renter": "awe",
    "borrower": "awe",
    "loanType": "long_term",
    "loanDate": "2025-08-08T16:43:08.002Z",
    "dueDate": "2025-08-07",
    "returnDate": "2025-08-08T16:43:14.552Z"
  },
  {
    "id": "9f55a89e-dcc3-4192-8667-9eebff8d3363",
    "stockId": "535078d3-0a65-4976-97f1-d6c26e164909",
    "productId": "9b85324b-c3d3-4230-845a-d2aa587fa57b",
    "locationId": "17488639384598c7b98b4c61cb8",
    "renter": "awe",
    "borrower": "awe",
    "loanType": "long_term",
    "loanDate": "2025-08-08T16:43:08.002Z",
    "dueDate": "2025-08-07",
    "returnDate": "2025-08-08T16:43:14.552Z"
  },
  {
    "id": "b4945306-8ee3-411b-9d6e-5a5ed05666e1",
    "stockId": "f16e855b-8d55-4ea3-9952-9b1224da6044",
    "productId": "9b85324b-c3d3-4230-845a-d2aa587fa57b",
    "locationId": "17488639384598c7b98b4c61cb8",
    "renter": "awe",
    "borrower": "awe",
    "loanType": "long_term",
    "loanDate": "2025-08-08T16:43:08.002Z",
    "dueDate": "2025-08-07",
    "returnDate": "2025-08-08T16:43:14.552Z"
  }
]